pyganalytics/GoogleAnalytics.py
pyganalytics/MetaGoogleAnalytics.py
pyganalytics/__init__.py
pyganalytics/mapping.py
pyganalytics/metric_dim_example.py
pyganalytics/core/__init__.py
pyganalytics/core/extract/__init__.py
pyganalytics/core/extract/api.py
pyganalytics/core/extract/config.py
pyganalytics/core/extract/date.py
pyganalytics/core/extract/manage_view.py
pyganalytics/core/load/__init__.py
pyganalytics/core/load/to_database.py
pyganalytics/core/transform/__init__.py
pyganalytics/core/transform/core.py
pyganalytics/core/transform/extract.py
pyganalytics/core/transform/path.py
pyganalytics-0.1.19.dist-info/LICENSE
pyganalytics-0.1.19.dist-info/METADATA
pyganalytics-0.1.19.dist-info/WHEEL
pyganalytics-0.1.19.dist-info/top_level.txt
pyganalytics-0.1.19.dist-info/RECORD
