Metadata-Version: 2.1
Name: pyganalytics
Version: 0.1.19
Summary: Easily get data from Google Analytics
Home-page: https://github.com/dacker-team/pyganalytics
Author: Dacker
Author-email: hello@dacker.co
License: UNKNOWN
Keywords: get data google analytics easy
Platform: UNKNOWN
Requires-Python: >=3
Requires-Dist: dbstream (>=0.0.12)
Requires-Dist: PyYAML (>=5.1)
Requires-Dist: isoweek (>=1.3.3)
Requires-Dist: googleauthentication (>=0.0.10)
